yta_video_frame_time/__init__.py
yta_video_frame_time/decorators.py
yta_video_frame_time/interval.py
yta_video_frame_time/t_fraction.py
yta_video_frame_time-0.0.27.dist-info/licenses/LICENSE
yta_video_frame_time-0.0.27.dist-info/METADATA
yta_video_frame_time-0.0.27.dist-info/WHEEL
yta_video_frame_time-0.0.27.dist-info/RECORD
