Metadata-Version: 2.4
Name: yta-video-frame-time
Version: 0.0.27
Summary: Youtube Autonomous Video Frame Time Module
License-File: LICENSE
Author: danialcala94
Author-email: danielalcalavalera@gmail.com
Requires-Python: ==3.9
Classifier: Programming Language :: Python :: 3
Classifier: Programming Language :: Python :: 3.9
Requires-Dist: quicktions (>=0.0.1,<9.0.0)
Requires-Dist: yta_validation (>=0.0.1,<1.0.0)
